{
    "type": "minecraft:crafting_shaped",
    "key": {
        "X": {
            "item": "astral_mekanism:essential_heat_generator"
        },
        "A": {
            "item": "astral_mekanism:alloy_convergent"
        },
        "C": {
            "item": "astral_mekanism:resonance_control_circuit"
        },
        "I": {
            "tag": "forge:ingots/bronze"
        }
    },
    "pattern": [
        "ACA",
        "IXI",
        "ACA"
    ],
    "result": {
        "item": "astral_mekanism:cosmic_heat_generator",
        "count": 1
    }
}